[{
	"image_Id": "ed1b1485-9b224c75-b2da-9ef44898b822",
	"unit_Id": "35b0ad51-8b75-4790-ad9b-449896005f4a",
	"camera_Id": "e7269804-1fec-4600-8b13-a48517ef0e2f",
	"ipaddress": "192.168.52.63",
	"timestamp": "2019-07-30",
	"fNumber": 15.25,
	"fps": 15,
	"stereo": true,
	"nXPixels": 78,
	"nYPixels": 45,
	"gain": 3,
	"exposure": 14,
	"white_balance_blue": 78,
	"white_balance_red": 36,
	"stereoSep": 45.26
},{
	"image_Id": "168a1f7c-8f22-4b4e-a581-94ede640f17c",
	"unit_Id": "69baaccb-83a3-416d-ac5c-8d28df820b52",
	"camera_Id": "5976580d-1dea-4fde-95dd-d2c65bb0d03a",
	"ipaddress": "192.168.52.163",
	"timestamp": "2019-07-31",
	"fNumber": 15.25,
	"fps": 30,
	"stereo": true,
	"nXPixels": 78,
	"nYPixels": 45,
	"gain": 3,
	"exposure": 14,
	"white_balance_blue": 78,
	"white_balance_red": 36,
	"stereoSep": 45.26
}]
